n64img/__init__.py
n64img/image.py
n64img/iter.py
test/__init__.py
test/test_endian.py
test/test_image.py
n64img-0.3.3.dist-info/LICENSE
n64img-0.3.3.dist-info/METADATA
n64img-0.3.3.dist-info/WHEEL
n64img-0.3.3.dist-info/top_level.txt
n64img-0.3.3.dist-info/RECORD
