Metadata-Version: 2.1
Name: n64img
Version: 0.3.3
Summary: N64 image format library
Home-page: https://github.com/decompals/n64img
Author: Decompals
License: MIT
Project-URL: Source, https://github.com/decompals/n64img
Project-URL: Bug Tracker, https://github.com/decompals/n64img/issues
License-File: LICENSE
